Metadata-Version: 1.2
Name: RevealMilkyWay
Version: 0.1
Summary: Some frequently used functions for studying the Milky Way
Home-page: UNKNOWN
Author: htian
Author-email: htian_astro@163.com
Maintainer: htian
Maintainer-email: htian_astro@163.com
License: BSD License
Platform: UNKNOWN
